{"cameraMode":{"drawMode":0,"name":"Shaded","section":"Shading Mode"},"sceneLighting":true,"audioPlay":false,"sceneViewState":{"m_AlwaysRefresh":false,"showFog":true,"showSkybox":true,"showFlares":true,"showImageEffects":true,"showParticleSystems":true,"showVisualEffectGraphs":true,"m_FxEnabled":true},"in2DMode":false,"pivot":{"x":-4.218968391418457,"y":1.3272464275360108,"z":2.8440098762512209},"rotation":{"x":0.04065979644656181,"y":-0.9340736865997315,"z":0.11292306333780289,"w":0.33632004261016848},"size":4.414010524749756,"orthographic":false}